SuperSimpleConfig/__init__.py
SuperSimpleConfig-2023.12.13.dist-info/LICENSE
SuperSimpleConfig-2023.12.13.dist-info/METADATA
SuperSimpleConfig-2023.12.13.dist-info/WHEEL
SuperSimpleConfig-2023.12.13.dist-info/entry_points.txt
SuperSimpleConfig-2023.12.13.dist-info/top_level.txt
SuperSimpleConfig-2023.12.13.dist-info/RECORD
