Metadata-Version: 2.1
Name: SuperSimpleConfig
Version: 2023.12.13
Summary: Reads user configuration files that written in an extremely simple way
Home-page: https://github.com/shengj1ang/SuperSimpleConfig
License: UNKNOWN
Platform: UNKNOWN
License-File: LICENSE
